redpepper/common/__init__.py
redpepper/common/config.py
redpepper/common/connection.py
redpepper/common/errors.py
redpepper/common/messages.py
redpepper/common/operations.py
redpepper/common/requests.py
redpepper/common/rpc.py
redpepper/common/slot.py
redpepper_common-0.3.3.dist-info/METADATA
redpepper_common-0.3.3.dist-info/WHEEL
redpepper_common-0.3.3.dist-info/RECORD
